Metadata-Version: 1.0
Name: bottle-websocket
Version: 0.2.5
Summary: WebSockets for bottle
Home-page: UNKNOWN
Author: Zach Kelling
Author-email: zeekayy@gmail.com
License: UNKNOWN
Platform: UNKNOWN
